{
  "id": "pans",
  "title": "🍳 pAn's",
  "url": "https://www.pans.at/tagesmenue/",
  "type": "full",
  "cuisine": [
    "bistro"
  ],
  "outdoor": true,
  "coordinates": {
    "lat": 48.2242,
    "lon": 16.3969
  },
  "fetchedAt": "2026-03-24T10:10:32.893Z",
  "error": null,
  "days": {
    "Dienstag": {
      "categories": [
        {
          "name": "Menu",
          "items": [
            {
              "title": "Sweet potato coconut milk (vegan) soup",
              "price": null,
              "tags": [
                "Vegan"
              ],
              "allergens": "L,N,O",
              "description": null
            },
            {
              "title": "Lasagna Bolognese (beef) with mozzarella and salad",
              "price": "11,90 €",
              "tags": [
                "Rindfleisch"
              ],
              "allergens": "A,C,M,0,6",
              "description": null
            },
            {
              "title": "Wild garlic risotto with salad and parmesan (L,6c,N,0,M)",
              "price": "11,90 €",
              "tags": [],
              "allergens": null,
              "description": null
            }
          ]
        },
        {
          "name": "Daily recommendations",
          "items": [
            {
              "title": "Hokkaido pumpkin coconut milk soup (vegan)",
              "price": "5,50 € / 7,50 €",
              "tags": [
                "Vegan"
              ],
              "allergens": "O,N,L",
              "description": null
            },
            {
              "title": "Salad bowl with avocado, sheep cheese and hummus",
              "price": "16,90 €",
              "tags": [],
              "allergens": "0,M,G,N",
              "description": null
            },
            {
              "title": "Wild garlic penne a la cream (A,‚C,G,O,L,N)",
              "price": "16,90 €",
              "tags": [],
              "allergens": null,
              "description": null
            },
            {
              "title": "Chili con Tofu (Vegan) with fried potatoes",
              "price": "16,90 €",
              "tags": [
                "Vegan"
              ],
              "allergens": "O,L,N",
              "description": null
            },
            {
              "title": "Cevapcici with fried potatoes and salad with mustard onion",
              "price": "17,90 €",
              "tags": [],
              "allergens": "C,O,M",
              "description": null
            },
            {
              "title": "Couscous salad with grilled chicken fillet and sheep's cheese",
              "price": "18,90 €",
              "tags": [
                "Huhn"
              ],
              "allergens": "A,0,M,6",
              "description": null
            },
            {
              "title": "Fried slices grilled with buttered olives and parsley potatoes",
              "price": "24,90 €",
              "tags": [],
              "allergens": "0,6",
              "description": null
            },
            {
              "title": "Grilled salmon fillet with parsley potatoes and salad",
              "price": "22,90 €",
              "tags": [
                "Fisch"
              ],
              "allergens": "D,O,M,G",
              "description": null
            },
            {
              "title": "Chocolate cakes with chocolate sauce and whipped cream",
              "price": "7,20 €",
              "tags": [],
              "allergens": "A,C,G",
              "description": null
            }
          ]
        }
      ]
    }
  }
}
